[
  {
    "file": "spec/templates/methods/class_methods.coffee",
    "class": {
      "className": "TestClassMethods",
      "name": "TestClassMethods",
      "namespace": ""
    },
    "methods": [
      {
        "type": "class",
        "signature": "+ (void) <strong>helper</strong>()",
        "name": "helper",
        "bound": false,
        "parameters": []
      },
      {
        "type": "class",
        "signature": "+ (void) <strong>another</strong>(a, b)",
        "name": "another",
        "bound": false,
        "parameters": [
          {
            "name": "a",
            "splat": false
          },
          {
            "name": "b",
            "splat": false
          }
        ]
      },
      {
        "type": "class",
        "signature": "+ (void) <strong>withDefault</strong>(a = 2, c, d = 'hi', d, e = { a: 2 }, f = new TestClassMethods())",
        "name": "withDefault",
        "bound": false,
        "parameters": [
          {
            "name": "a",
            "default": "2",
            "splat": false
          },
          {
            "name": "c",
            "splat": false
          },
          {
            "name": "d",
            "default": "'hi'",
            "splat": false
          },
          {
            "name": "d",
            "splat": false
          },
          {
            "name": "e",
            "default": "{\n  a: 2\n}",
            "splat": false
          },
          {
            "name": "f",
            "default": "new TestClassMethods()",
            "splat": false
          }
        ]
      },
      {
        "type": "class",
        "signature": "+ (void) <strong>nowWithSpalt</strong>(foo, bar...)",
        "name": "nowWithSpalt",
        "bound": false,
        "parameters": [
          {
            "name": "foo",
            "splat": false
          },
          {
            "name": "bar",
            "splat": true
          }
        ]
      },
      {
        "type": "class",
        "signature": "+ (void) <strong>andSoDoesThis</strong>(foo, bar)",
        "name": "andSoDoesThis",
        "bound": false,
        "parameters": [
          {
            "name": "foo",
            "splat": false
          },
          {
            "name": "bar",
            "splat": false
          }
        ]
      }
    ],
    "variables": [],
    "properties": []
  }
]
